falu/__init__.py
falu/errors.py
falu/list_options.py
falu/query_values.py
falu/range_filtering_options.py
falu/version.py
falu/client/__init__.py
falu/client/api_client.py
falu/client/falu_model.py
falu/generic/__init__.py
falu/generic/delete_api_request.py
falu/generic/get_api_request.py
falu/generic/patch_api_request.py
falu/generic/post_api_request.py
falu/services/__init__.py
falu/services/customers.py
falu/services/events.py
falu/services/file_links.py
falu/services/files.py
falu/services/identity_verification_reports.py
falu/services/identity_verifications.py
falu/services/message_batches.py
falu/services/message_streams.py
falu/services/message_suppressions.py
falu/services/message_templates.py
falu/services/messages.py
falu/services/money.py
falu/services/payment_authorizations.py
falu/services/payment_refunds.py
falu/services/payments.py
falu/services/temporary_keys.py
falu/services/terminal_configurations.py
falu/services/terminal_devices.py
falu/services/terminal_locations.py
falu/services/transfer_reversals.py
falu/services/transfers.py
falu/services/visitor_destinations.py
falu/services/visitors.py
falu/services/visits.py
falu/services/wallet.py
falu/services/wallet_transactions.py
falu/services/webhook_endpoints.py
falu-1.2.0.dist-info/LICENSE
falu-1.2.0.dist-info/METADATA
falu-1.2.0.dist-info/WHEEL
falu-1.2.0.dist-info/top_level.txt
falu-1.2.0.dist-info/RECORD
